PyLogger/__init__.py
PyLogger/config.py
PyLogger/log_handler.py
PyLogger/logger.py
PyLogger3-0.1.4.dist-info/LICENSE
PyLogger3-0.1.4.dist-info/METADATA
PyLogger3-0.1.4.dist-info/WHEEL
PyLogger3-0.1.4.dist-info/top_level.txt
PyLogger3-0.1.4.dist-info/RECORD
