Metadata-Version: 2.1
Name: PyLogger3
Version: 0.1.4
Summary: This is the simplest logger.
Author: macht1212
Classifier: Programming Language :: Python :: 3.11
Classifier: License :: OSI Approved :: MIT License
Classifier: Operating System :: OS Independent
Requires-Python: >=3.11
License-File: LICENSE
